{
  "fIDocuments": [
    {
      "id": "a26a8b1c20a74d608128aaa2a75648d2",
      "docType": "expense",
      "companyId": "821599",
      "entityId": "t0171945nik5",
      "companyUuid": "070fde04-3e0c-4716-89fd-6026ae292ed0",
      "erpSystemId": "",
      "document": {
        "employee": {
          "employeeId": "1017001",
          "employeeFirstName": "Dp1",
          "employeeLastName": "CTE",
          "employeeMI": null,
          "employeeOrgUnit1Code": "Q16CLNT500",
          "employeeOrgUnit2Code": "0021",
          "employeeOrgUnit3Code": "CC",
          "employeeOrgUnit4Code": "21-BELLEV1",
          "employeeOrgUnit5Code": null,
          "employeeOrgUnit6Code": null,
          "employeeOrgUnit1Value": "EhP6TestSysTravelCareerOD",
          "employeeOrgUnit2Value": "TemOD US 2",
          "employeeOrgUnit3Value": "Cost Center",
          "employeeOrgUnit4Value": "TemOD 0021-Bellevue1",
          "employeeOrgUnit5Value": null,
          "employeeOrgUnit6Value": null,
          "employeeCustom1Code": null,
          "employeeCustom2Code": null,
          "employeeCustom3Code": null,
          "employeeCustom4Code": null,
          "employeeCustom5Code": null,
          "employeeCustom6Code": null,
          "employeeCustom7Code": null,
          "employeeCustom8Code": null,
          "employeeCustom9Code": null,
          "employeeCustom10Code": null,
          "employeeCustom11Code": null,
          "employeeCustom12Code": null,
          "employeeCustom13Code": null,
          "employeeCustom14Code": null,
          "employeeCustom15Code": null,
          "employeeCustom16Code": null,
          "employeeCustom17Code": "1017001",
          "employeeCustom18Code": null,
          "employeeCustom19Code": null,
          "employeeCustom20Code": null,
          "employeeCustom21Code": null,
          "employeeCustom1Value": null,
          "employeeCustom2Value": null,
          "employeeCustom3Value": null,
          "employeeCustom4Value": null,
          "employeeCustom5Value": null,
          "employeeCustom6Value": null,
          "employeeCustom7Value": null,
          "employeeCustom8Value": null,
          "employeeCustom9Value": null,
          "employeeCustom10Value": null,
          "employeeCustom11Value": null,
          "employeeCustom12Value": null,
          "employeeCustom13Value": null,
          "employeeCustom14Value": null,
          "employeeCustom15Value": null,
          "employeeCustom16Value": null,
          "employeeCustom17Value": null,
          "employeeCustom18Value": null,
          "employeeCustom19Value": null,
          "employeeCustom20Value": null,
          "employeeCustom21Value": null
        },
        "report": {
          "requestId": [],
          "employeeCurrencyAlphaCode": "USD",
          "reportId": "815EF4FB5B4448A9B09E",
          "totalApprovedAmount": 305,
          "isTest": "N",
          "ledgerCode": "DEFAULT",
          "reportKey": 5183,
          "reportName": "FI use-case test example 6.2.4",
          "reportStartDate": null,
          "reportEndDate": null,
          "payrollPayIndicator": "N",
          "payrollPaymentClearingAccountCode": null,
          "cashAdvanceReturnsAmount": 0,
          "revisionNumber": "1",
          "versionId": "4",
          "homeCountryCode": "US",
          "reportSubmitDate": "2019-06-05T23:37:20.303Z",
          "reportUserDefinedDate": "2019-06-03T00:00:00.000Z",
          "reportPaymentProcessingDate": "2019-06-05T23:37:20.590Z",
          "reportCreationDate": "2019-06-03T19:15:08.920Z",
          "reportCustom1Code": null,
          "reportCustom2Code": null,
          "reportCustom3Code": null,
          "reportCustom4Code": null,
          "reportCustom5Code": null,
          "reportCustom6Code": null,
          "reportCustom7Code": null,
          "reportCustom8Code": null,
          "reportCustom9Code": null,
          "reportCustom10Code": null,
          "reportCustom11Code": null,
          "reportCustom12Code": null,
          "reportCustom13Code": "305.00",
          "reportCustom14Code": null,
          "reportCustom15Code": null,
          "reportCustom16Code": null,
          "reportCustom17Code": "1017001",
          "reportCustom18Code": null,
          "reportCustom19Code": null,
          "reportCustom20Code": null,
          "reportCustom1Value": null,
          "reportCustom2Value": null,
          "reportCustom3Value": null,
          "reportCustom4Value": null,
          "reportCustom5Value": null,
          "reportCustom6Value": null,
          "reportCustom7Value": null,
          "reportCustom8Value": null,
          "reportCustom9Value": null,
          "reportCustom10Value": null,
          "reportCustom11Value": null,
          "reportCustom12Value": null,
          "reportCustom13Value": null,
          "reportCustom14Value": null,
          "reportCustom15Value": null,
          "reportCustom16Value": null,
          "reportCustom17Value": null,
          "reportCustom18Value": null,
          "reportCustom19Value": null,
          "reportCustom20Value": null,
          "reportOrgUnit1Code": "Q16CLNT500",
          "reportOrgUnit2Code": "0021",
          "reportOrgUnit3Code": "CC",
          "reportOrgUnit4Code": "21-BELLEV1",
          "reportOrgUnit5Code": null,
          "reportOrgUnit6Code": null,
          "reportOrgUnit1Value": "EhP6TestSysTravelCareerOD",
          "reportOrgUnit2Value": "TemOD US 2",
          "reportOrgUnit3Value": "Cost Center",
          "reportOrgUnit4Value": "TemOD 0021-Bellevue1",
          "reportOrgUnit5Value": null,
          "reportOrgUnit6Value": null
        },
        "expenseEntry": [
          {
            "expensePayIndicator": "N",
            "clearingAccountCode": null,
            "cardProgramTypeCode": null,
            "entryApprovedAmount": 35,
            "entryId": "DBE3B047F0EDC14283E92EFFABB666CE",
            "entryDescription": "Out-of-pocket expense",
            "entryVendorCode": null,
            "entryCustom1Value": null,
            "entryCustom2Value": null,
            "entryCustom3Value": null,
            "entryCustom4Value": null,
            "entryCustom5Value": null,
            "entryCustom6Value": null,
            "entryCustom7Value": null,
            "entryCustom8Value": null,
            "entryCustom9Value": null,
            "entryCustom10Value": null,
            "entryCustom11Value": null,
            "entryCustom12Value": null,
            "entryCustom13Value": null,
            "entryCustom14Value": null,
            "entryCustom15Value": null,
            "entryCustom16Value": null,
            "entryCustom17Value": null,
            "entryCustom18Value": null,
            "entryCustom19Value": null,
            "entryCustom20Value": null,
            "entryCustom21Value": null,
            "entryCustom22Value": null,
            "entryCustom23Value": null,
            "entryCustom24Value": null,
            "entryCustom25Value": null,
            "entryCustom26Value": null,
            "entryCustom27Value": null,
            "entryCustom28Value": null,
            "entryCustom29Value": null,
            "entryCustom30Value": null,
            "entryCustom31Value": null,
            "entryCustom32Value": null,
            "entryCustom33Value": null,
            "entryCustom34Value": null,
            "entryCustom35Value": null,
            "entryCustom36Value": null,
            "entryCustom37Value": null,
            "entryCustom38Value": null,
            "entryCustom39Value": null,
            "entryCustom40Value": null,
            "entryOrgUnit1Value": "EhP6TestSysTravelCareerOD",
            "entryOrgUnit2Value": "TemOD US 2",
            "entryOrgUnit3Value": "Cost Center",
            "entryOrgUnit4Value": "TemOD 0021-Bellevue1",
            "entryOrgUnit5Value": null,
            "entryOrgUnit6Value": null,
            "entryLocationName": null,
            "entryReceiptId": null,
            "entryElectronicReceiptId": null,
            "entryCustom4Code": null,
            "entryCustom5Code": null,
            "entryCustom6Code": null,
            "entryCustom7Code": null,
            "entryCustom8Code": null,
            "entryCustom9Code": null,
            "entryCustom10Code": null,
            "entryCustom11Code": null,
            "entryCustom12Code": null,
            "entryCustom13Code": null,
            "entryCustom14Code": null,
            "entryCustom15Code": null,
            "entryCustom16Code": null,
            "entryCustom17Code": null,
            "entryCustom18Code": null,
            "entryCustom19Code": null,
            "entryCustom20Code": null,
            "entryCustom21Code": null,
            "entryCustom22Code": null,
            "entryCustom23Code": null,
            "entryCustom24Code": null,
            "entryCustom25Code": null,
            "entryCustom26Code": null,
            "entryCustom27Code": null,
            "entryCustom28Code": null,
            "entryCustom29Code": null,
            "entryCustom30Code": null,
            "entryCustom31Code": null,
            "entryCustom32Code": null,
            "entryCustom33Code": null,
            "entryCustom34Code": null,
            "entryCustom35Code": null,
            "entryCustom36Code": null,
            "entryCustom37Code": null,
            "entryCustom38Code": "",
            "entryCustom39Code": "0.00000000",
            "entryCustom40Code": "35.00000000",
            "reportEntryTransactionAmount": 35,
            "entryLocationCityName": null,
            "entryCountrySubCode": null,
            "entryIsBillable": "N",
            "entryOrgUnit1Code": "Q16CLNT500",
            "entryOrgUnit2Code": "0021",
            "offsetPayType": "N",
            "entryCountryCode": null,
            "entryUuid": null,
            "entrySupplierTaxID": null,
            "entryCustom1Code": null,
            "entryCustom2Code": null,
            "entryCustom3Code": null,
            "entryOrgUnit3Code": "CC",
            "entryOrgUnit4Code": "21-BELLEV1",
            "entryOrgUnit5Code": null,
            "entryOrgUnit6Code": null,
            "cardAccountID": null,
            "cardTransactionID": null,
            "cardTransactionAmount": null,
            "cardTransactionCurrency": null,
            "cardTransactionPostedAmount": null,
            "cardTransactionPostedCurrency": null,
            "allocation": [
              {
                "allocationPercentage": 100,
                "allocationId": "19756F503851D44D96DDC00872249A0B",
                "allocationCustom1Code": "Q16CLNT500",
                "allocationCustom2Code": "0021",
                "allocationCustom3Code": "CC",
                "allocationCustom4Code": "21-BELLEV1",
                "allocationCustom5Code": null,
                "allocationCustom6Code": null,
                "allocationCustom7Code": null,
                "allocationCustom8Code": null,
                "allocationCustom9Code": "",
                "allocationCustom10Code": null,
                "allocationCustom11Code": null,
                "allocationCustom12Code": null,
                "allocationCustom13Code": null,
                "allocationCustom14Code": null,
                "allocationCustom15Code": null,
                "allocationCustom16Code": null,
                "allocationCustom17Code": null,
                "allocationCustom18Code": null,
                "allocationCustom19Code": null,
                "allocationCustom20Code": null,
                "allocationCustom1Value": "EhP6TestSysTravelCareerOD",
                "allocationCustom2Value": "TemOD US 2",
                "allocationCustom3Value": "Cost Center",
                "allocationCustom4Value": "TemOD 0021-Bellevue1",
                "allocationCustom5Value": null,
                "allocationCustom6Value": null,
                "allocationCustom7Value": null,
                "allocationCustom8Value": null,
                "allocationCustom9Value": null,
                "allocationCustom10Value": null,
                "allocationCustom11Value": null,
                "allocationCustom12Value": null,
                "allocationCustom13Value": null,
                "allocationCustom14Value": null,
                "allocationCustom15Value": null,
                "allocationCustom16Value": null,
                "allocationCustom17Value": null,
                "allocationCustom18Value": null,
                "allocationCustom19Value": null,
                "allocationCustom20Value": null,
                "journal": [
                  {
                    "amountGross": 35,
                    "amountGrossCard": null,
                    "journalAccountCode": "474230",
                    "journalPayee": "EMPL",
                    "journalPayer": "COMP",
                    "cardTransactionReferenceNumber": null,
                    "amountNetOfReclaim": 35,
                    "amountNetOfTax": 35,
                    "taxGuid": [],
                    "accountingTransactionType": null
                  }
                ],
                "tax": []
              }
            ],
            "liabilityAccountCode": null,
            "entryExchangeRateDirection": "M",
            "entryReceiptType": "N",
            "entryVendorDescription": "Taxi",
            "entryIsPersonal": "N",
            "legacyEntryId": 4291,
            "expenseTypeName": "Taxi",
            "entryDate": "2019-05-29T00:00:00.000Z",
            "entryCurrAlphaCode": "USD",
            "entryExchangeRate": 1,
            "expenseTypeCode": "TAXIX",
            "cardStatementPeriodStartDate": null,
            "cardStatementPeriodEndDate": null,
            "reportEntryPatKey": "CASH"
          },
          {
            "expensePayIndicator": "N",
            "clearingAccountCode": "199999",
            "cardProgramTypeCode": null,
            "entryApprovedAmount": 125,
            "entryId": "95C3C97F4149CF45949DECE8C5171478",
            "entryDescription": null,
            "entryVendorCode": "Marriott Hotels",
            "entryCustom1Value": null,
            "entryCustom2Value": null,
            "entryCustom3Value": null,
            "entryCustom4Value": null,
            "entryCustom5Value": null,
            "entryCustom6Value": null,
            "entryCustom7Value": null,
            "entryCustom8Value": null,
            "entryCustom9Value": null,
            "entryCustom10Value": null,
            "entryCustom11Value": null,
            "entryCustom12Value": null,
            "entryCustom13Value": null,
            "entryCustom14Value": null,
            "entryCustom15Value": null,
            "entryCustom16Value": null,
            "entryCustom17Value": null,
            "entryCustom18Value": null,
            "entryCustom19Value": null,
            "entryCustom20Value": null,
            "entryCustom21Value": null,
            "entryCustom22Value": null,
            "entryCustom23Value": null,
            "entryCustom24Value": null,
            "entryCustom25Value": null,
            "entryCustom26Value": null,
            "entryCustom27Value": null,
            "entryCustom28Value": null,
            "entryCustom29Value": null,
            "entryCustom30Value": null,
            "entryCustom31Value": null,
            "entryCustom32Value": null,
            "entryCustom33Value": null,
            "entryCustom34Value": null,
            "entryCustom35Value": null,
            "entryCustom36Value": null,
            "entryCustom37Value": null,
            "entryCustom38Value": null,
            "entryCustom39Value": null,
            "entryCustom40Value": null,
            "entryOrgUnit1Value": "EhP6TestSysTravelCareerOD",
            "entryOrgUnit2Value": "TemOD US 2",
            "entryOrgUnit3Value": "Cost Center",
            "entryOrgUnit4Value": "TemOD 0021-Bellevue1",
            "entryOrgUnit5Value": null,
            "entryOrgUnit6Value": null,
            "entryLocationName": "San Francisco",
            "entryReceiptId": null,
            "entryElectronicReceiptId": null,
            "entryCustom4Code": null,
            "entryCustom5Code": null,
            "entryCustom6Code": null,
            "entryCustom7Code": null,
            "entryCustom8Code": null,
            "entryCustom9Code": null,
            "entryCustom10Code": null,
            "entryCustom11Code": null,
            "entryCustom12Code": null,
            "entryCustom13Code": null,
            "entryCustom14Code": null,
            "entryCustom15Code": null,
            "entryCustom16Code": null,
            "entryCustom17Code": null,
            "entryCustom18Code": null,
            "entryCustom19Code": null,
            "entryCustom20Code": null,
            "entryCustom21Code": null,
            "entryCustom22Code": null,
            "entryCustom23Code": null,
            "entryCustom24Code": null,
            "entryCustom25Code": null,
            "entryCustom26Code": null,
            "entryCustom27Code": null,
            "entryCustom28Code": null,
            "entryCustom29Code": null,
            "entryCustom30Code": null,
            "entryCustom31Code": null,
            "entryCustom32Code": null,
            "entryCustom33Code": null,
            "entryCustom34Code": null,
            "entryCustom35Code": "US",
            "entryCustom36Code": null,
            "entryCustom37Code": null,
            "entryCustom38Code": "",
            "entryCustom39Code": "0.00000000",
            "entryCustom40Code": "125.00000000",
            "reportEntryTransactionAmount": 125,
            "entryLocationCityName": "San Francisco",
            "entryCountrySubCode": "US-CA",
            "entryIsBillable": "N",
            "entryOrgUnit1Code": "Q16CLNT500",
            "entryOrgUnit2Code": "0021",
            "offsetPayType": "N",
            "entryCountryCode": "US",
            "entryUuid": null,
            "entrySupplierTaxID": null,
            "entryCustom1Code": null,
            "entryCustom2Code": null,
            "entryCustom3Code": null,
            "entryOrgUnit3Code": "CC",
            "entryOrgUnit4Code": "21-BELLEV1",
            "entryOrgUnit5Code": null,
            "entryOrgUnit6Code": null,
            "cardAccountID": null,
            "cardTransactionID": null,
            "cardTransactionAmount": null,
            "cardTransactionCurrency": null,
            "cardTransactionPostedAmount": null,
            "cardTransactionPostedCurrency": null,
            "allocation": [
              {
                "allocationPercentage": 100,
                "allocationId": "89C5DE0AB4BC4A4CBF4D5AE750A3A8E7",
                "allocationCustom1Code": "Q16CLNT500",
                "allocationCustom2Code": "0021",
                "allocationCustom3Code": "CC",
                "allocationCustom4Code": "21-BELLEV1",
                "allocationCustom5Code": null,
                "allocationCustom6Code": null,
                "allocationCustom7Code": null,
                "allocationCustom8Code": null,
                "allocationCustom9Code": "",
                "allocationCustom10Code": null,
                "allocationCustom11Code": null,
                "allocationCustom12Code": null,
                "allocationCustom13Code": null,
                "allocationCustom14Code": null,
                "allocationCustom15Code": null,
                "allocationCustom16Code": null,
                "allocationCustom17Code": null,
                "allocationCustom18Code": null,
                "allocationCustom19Code": null,
                "allocationCustom20Code": null,
                "allocationCustom1Value": "EhP6TestSysTravelCareerOD",
                "allocationCustom2Value": "TemOD US 2",
                "allocationCustom3Value": "Cost Center",
                "allocationCustom4Value": "TemOD 0021-Bellevue1",
                "allocationCustom5Value": null,
                "allocationCustom6Value": null,
                "allocationCustom7Value": null,
                "allocationCustom8Value": null,
                "allocationCustom9Value": null,
                "allocationCustom10Value": null,
                "allocationCustom11Value": null,
                "allocationCustom12Value": null,
                "allocationCustom13Value": null,
                "allocationCustom14Value": null,
                "allocationCustom15Value": null,
                "allocationCustom16Value": null,
                "allocationCustom17Value": null,
                "allocationCustom18Value": null,
                "allocationCustom19Value": null,
                "allocationCustom20Value": null,
                "journal": [
                  {
                    "amountGross": 125,
                    "amountGrossCard": null,
                    "journalAccountCode": "474230",
                    "journalPayee": "CBCP",
                    "journalPayer": "COMP",
                    "cardTransactionReferenceNumber": null,
                    "amountNetOfReclaim": 125,
                    "amountNetOfTax": 125,
                    "taxGuid": [],
                    "accountingTransactionType": null
                  }
                ],
                "tax": []
              }
            ],
            "liabilityAccountCode": null,
            "entryExchangeRateDirection": "M",
            "entryReceiptType": "N",
            "entryVendorDescription": "Marriott Hotels",
            "entryIsPersonal": "N",
            "legacyEntryId": 4253,
            "expenseTypeName": "Room Rate",
            "entryDate": "2019-06-03T00:00:00.000Z",
            "entryCurrAlphaCode": "USD",
            "entryExchangeRate": 1,
            "expenseTypeCode": "LODNG",
            "cardStatementPeriodStartDate": null,
            "cardStatementPeriodEndDate": null,
            "reportEntryPatKey": "1000"
          },
          {
            "expensePayIndicator": "N",
            "clearingAccountCode": "199999",
            "cardProgramTypeCode": null,
            "entryApprovedAmount": 20,
            "entryId": "52F2FB67BBD8D243A4C374FE7E508207",
            "entryDescription": null,
            "entryVendorCode": "Marriott Hotels",
            "entryCustom1Value": null,
            "entryCustom2Value": null,
            "entryCustom3Value": null,
            "entryCustom4Value": null,
            "entryCustom5Value": null,
            "entryCustom6Value": null,
            "entryCustom7Value": null,
            "entryCustom8Value": null,
            "entryCustom9Value": null,
            "entryCustom10Value": null,
            "entryCustom11Value": null,
            "entryCustom12Value": null,
            "entryCustom13Value": null,
            "entryCustom14Value": null,
            "entryCustom15Value": null,
            "entryCustom16Value": null,
            "entryCustom17Value": null,
            "entryCustom18Value": null,
            "entryCustom19Value": null,
            "entryCustom20Value": null,
            "entryCustom21Value": null,
            "entryCustom22Value": null,
            "entryCustom23Value": null,
            "entryCustom24Value": null,
            "entryCustom25Value": null,
            "entryCustom26Value": null,
            "entryCustom27Value": null,
            "entryCustom28Value": null,
            "entryCustom29Value": null,
            "entryCustom30Value": null,
            "entryCustom31Value": null,
            "entryCustom32Value": null,
            "entryCustom33Value": null,
            "entryCustom34Value": null,
            "entryCustom35Value": null,
            "entryCustom36Value": null,
            "entryCustom37Value": null,
            "entryCustom38Value": null,
            "entryCustom39Value": null,
            "entryCustom40Value": null,
            "entryOrgUnit1Value": "EhP6TestSysTravelCareerOD",
            "entryOrgUnit2Value": "TemOD US 2",
            "entryOrgUnit3Value": "Cost Center",
            "entryOrgUnit4Value": "TemOD 0021-Bellevue1",
            "entryOrgUnit5Value": null,
            "entryOrgUnit6Value": null,
            "entryLocationName": "San Francisco",
            "entryReceiptId": null,
            "entryElectronicReceiptId": null,
            "entryCustom4Code": null,
            "entryCustom5Code": null,
            "entryCustom6Code": null,
            "entryCustom7Code": null,
            "entryCustom8Code": null,
            "entryCustom9Code": null,
            "entryCustom10Code": null,
            "entryCustom11Code": null,
            "entryCustom12Code": null,
            "entryCustom13Code": null,
            "entryCustom14Code": null,
            "entryCustom15Code": null,
            "entryCustom16Code": null,
            "entryCustom17Code": null,
            "entryCustom18Code": null,
            "entryCustom19Code": null,
            "entryCustom20Code": null,
            "entryCustom21Code": null,
            "entryCustom22Code": null,
            "entryCustom23Code": null,
            "entryCustom24Code": null,
            "entryCustom25Code": null,
            "entryCustom26Code": null,
            "entryCustom27Code": null,
            "entryCustom28Code": null,
            "entryCustom29Code": null,
            "entryCustom30Code": null,
            "entryCustom31Code": null,
            "entryCustom32Code": null,
            "entryCustom33Code": null,
            "entryCustom34Code": null,
            "entryCustom35Code": "US",
            "entryCustom36Code": null,
            "entryCustom37Code": null,
            "entryCustom38Code": "",
            "entryCustom39Code": "0.00000000",
            "entryCustom40Code": "20.00000000",
            "reportEntryTransactionAmount": 20,
            "entryLocationCityName": "San Francisco",
            "entryCountrySubCode": "US-CA",
            "entryIsBillable": "N",
            "entryOrgUnit1Code": "Q16CLNT500",
            "entryOrgUnit2Code": "0021",
            "offsetPayType": "N",
            "entryCountryCode": "US",
            "entryUuid": null,
            "entrySupplierTaxID": null,
            "entryCustom1Code": null,
            "entryCustom2Code": null,
            "entryCustom3Code": null,
            "entryOrgUnit3Code": "CC",
            "entryOrgUnit4Code": "21-BELLEV1",
            "entryOrgUnit5Code": null,
            "entryOrgUnit6Code": null,
            "cardAccountID": null,
            "cardTransactionID": null,
            "cardTransactionAmount": null,
            "cardTransactionCurrency": null,
            "cardTransactionPostedAmount": null,
            "cardTransactionPostedCurrency": null,
            "allocation": [
              {
                "allocationPercentage": 100,
                "allocationId": "4D96AEE5B36FD74FB2B888CAD69E9A4A",
                "allocationCustom1Code": "Q16CLNT500",
                "allocationCustom2Code": "0021",
                "allocationCustom3Code": "CC",
                "allocationCustom4Code": "21-BELLEV1",
                "allocationCustom5Code": null,
                "allocationCustom6Code": null,
                "allocationCustom7Code": null,
                "allocationCustom8Code": null,
                "allocationCustom9Code": "",
                "allocationCustom10Code": null,
                "allocationCustom11Code": null,
                "allocationCustom12Code": null,
                "allocationCustom13Code": null,
                "allocationCustom14Code": null,
                "allocationCustom15Code": null,
                "allocationCustom16Code": null,
                "allocationCustom17Code": null,
                "allocationCustom18Code": null,
                "allocationCustom19Code": null,
                "allocationCustom20Code": null,
                "allocationCustom1Value": "EhP6TestSysTravelCareerOD",
                "allocationCustom2Value": "TemOD US 2",
                "allocationCustom3Value": "Cost Center",
                "allocationCustom4Value": "TemOD 0021-Bellevue1",
                "allocationCustom5Value": null,
                "allocationCustom6Value": null,
                "allocationCustom7Value": null,
                "allocationCustom8Value": null,
                "allocationCustom9Value": null,
                "allocationCustom10Value": null,
                "allocationCustom11Value": null,
                "allocationCustom12Value": null,
                "allocationCustom13Value": null,
                "allocationCustom14Value": null,
                "allocationCustom15Value": null,
                "allocationCustom16Value": null,
                "allocationCustom17Value": null,
                "allocationCustom18Value": null,
                "allocationCustom19Value": null,
                "allocationCustom20Value": null,
                "journal": [
                  {
                    "amountGross": 20,
                    "amountGrossCard": null,
                    "journalAccountCode": "474230",
                    "journalPayee": "CBCP",
                    "journalPayer": "COMP",
                    "cardTransactionReferenceNumber": null,
                    "amountNetOfReclaim": 20,
                    "amountNetOfTax": 20,
                    "taxGuid": [],
                    "accountingTransactionType": null
                  }
                ],
                "tax": []
              }
            ],
            "liabilityAccountCode": null,
            "entryExchangeRateDirection": "M",
            "entryReceiptType": "N",
            "entryVendorDescription": "Marriott Hotels",
            "entryIsPersonal": "N",
            "legacyEntryId": 4254,
            "expenseTypeName": "Dinner",
            "entryDate": "2019-06-03T00:00:00.000Z",
            "entryCurrAlphaCode": "USD",
            "entryExchangeRate": 1,
            "expenseTypeCode": "DINNR",
            "cardStatementPeriodStartDate": null,
            "cardStatementPeriodEndDate": null,
            "reportEntryPatKey": "1000"
          },
          {
            "expensePayIndicator": "N",
            "clearingAccountCode": "199999",
            "cardProgramTypeCode": null,
            "entryApprovedAmount": 125,
            "entryId": "88812B1956D9504FBEFCC832198C6BA0",
            "entryDescription": null,
            "entryVendorCode": "Marriott Hotels",
            "entryCustom1Value": null,
            "entryCustom2Value": null,
            "entryCustom3Value": null,
            "entryCustom4Value": null,
            "entryCustom5Value": null,
            "entryCustom6Value": null,
            "entryCustom7Value": null,
            "entryCustom8Value": null,
            "entryCustom9Value": null,
            "entryCustom10Value": null,
            "entryCustom11Value": null,
            "entryCustom12Value": null,
            "entryCustom13Value": null,
            "entryCustom14Value": null,
            "entryCustom15Value": null,
            "entryCustom16Value": null,
            "entryCustom17Value": null,
            "entryCustom18Value": null,
            "entryCustom19Value": null,
            "entryCustom20Value": null,
            "entryCustom21Value": null,
            "entryCustom22Value": null,
            "entryCustom23Value": null,
            "entryCustom24Value": null,
            "entryCustom25Value": null,
            "entryCustom26Value": null,
            "entryCustom27Value": null,
            "entryCustom28Value": null,
            "entryCustom29Value": null,
            "entryCustom30Value": null,
            "entryCustom31Value": null,
            "entryCustom32Value": null,
            "entryCustom33Value": null,
            "entryCustom34Value": null,
            "entryCustom35Value": null,
            "entryCustom36Value": null,
            "entryCustom37Value": null,
            "entryCustom38Value": null,
            "entryCustom39Value": null,
            "entryCustom40Value": null,
            "entryOrgUnit1Value": "EhP6TestSysTravelCareerOD",
            "entryOrgUnit2Value": "TemOD US 2",
            "entryOrgUnit3Value": "Cost Center",
            "entryOrgUnit4Value": "TemOD 0021-Bellevue1",
            "entryOrgUnit5Value": null,
            "entryOrgUnit6Value": null,
            "entryLocationName": "San Francisco",
            "entryReceiptId": null,
            "entryElectronicReceiptId": null,
            "entryCustom4Code": null,
            "entryCustom5Code": null,
            "entryCustom6Code": null,
            "entryCustom7Code": null,
            "entryCustom8Code": null,
            "entryCustom9Code": null,
            "entryCustom10Code": null,
            "entryCustom11Code": null,
            "entryCustom12Code": null,
            "entryCustom13Code": null,
            "entryCustom14Code": null,
            "entryCustom15Code": null,
            "entryCustom16Code": null,
            "entryCustom17Code": null,
            "entryCustom18Code": null,
            "entryCustom19Code": null,
            "entryCustom20Code": null,
            "entryCustom21Code": null,
            "entryCustom22Code": null,
            "entryCustom23Code": null,
            "entryCustom24Code": null,
            "entryCustom25Code": null,
            "entryCustom26Code": null,
            "entryCustom27Code": null,
            "entryCustom28Code": null,
            "entryCustom29Code": null,
            "entryCustom30Code": null,
            "entryCustom31Code": null,
            "entryCustom32Code": null,
            "entryCustom33Code": null,
            "entryCustom34Code": null,
            "entryCustom35Code": "US",
            "entryCustom36Code": null,
            "entryCustom37Code": null,
            "entryCustom38Code": "",
            "entryCustom39Code": "0.00000000",
            "entryCustom40Code": "125.00000000",
            "reportEntryTransactionAmount": 125,
            "entryLocationCityName": "San Francisco",
            "entryCountrySubCode": "US-CA",
            "entryIsBillable": "N",
            "entryOrgUnit1Code": "Q16CLNT500",
            "entryOrgUnit2Code": "0021",
            "offsetPayType": "N",
            "entryCountryCode": "US",
            "entryUuid": null,
            "entrySupplierTaxID": null,
            "entryCustom1Code": null,
            "entryCustom2Code": null,
            "entryCustom3Code": null,
            "entryOrgUnit3Code": "CC",
            "entryOrgUnit4Code": "21-BELLEV1",
            "entryOrgUnit5Code": null,
            "entryOrgUnit6Code": null,
            "cardAccountID": null,
            "cardTransactionID": null,
            "cardTransactionAmount": null,
            "cardTransactionCurrency": null,
            "cardTransactionPostedAmount": null,
            "cardTransactionPostedCurrency": null,
            "allocation": [
              {
                "allocationPercentage": 100,
                "allocationId": "EB519FF2601CB84F8EB15810A3AA7BC7",
                "allocationCustom1Code": "Q16CLNT500",
                "allocationCustom2Code": "0021",
                "allocationCustom3Code": "CC",
                "allocationCustom4Code": "21-BELLEV1",
                "allocationCustom5Code": null,
                "allocationCustom6Code": null,
                "allocationCustom7Code": null,
                "allocationCustom8Code": null,
                "allocationCustom9Code": "",
                "allocationCustom10Code": null,
                "allocationCustom11Code": null,
                "allocationCustom12Code": null,
                "allocationCustom13Code": null,
                "allocationCustom14Code": null,
                "allocationCustom15Code": null,
                "allocationCustom16Code": null,
                "allocationCustom17Code": null,
                "allocationCustom18Code": null,
                "allocationCustom19Code": null,
                "allocationCustom20Code": null,
                "allocationCustom1Value": "EhP6TestSysTravelCareerOD",
                "allocationCustom2Value": "TemOD US 2",
                "allocationCustom3Value": "Cost Center",
                "allocationCustom4Value": "TemOD 0021-Bellevue1",
                "allocationCustom5Value": null,
                "allocationCustom6Value": null,
                "allocationCustom7Value": null,
                "allocationCustom8Value": null,
                "allocationCustom9Value": null,
                "allocationCustom10Value": null,
                "allocationCustom11Value": null,
                "allocationCustom12Value": null,
                "allocationCustom13Value": null,
                "allocationCustom14Value": null,
                "allocationCustom15Value": null,
                "allocationCustom16Value": null,
                "allocationCustom17Value": null,
                "allocationCustom18Value": null,
                "allocationCustom19Value": null,
                "allocationCustom20Value": null,
                "journal": [
                  {
                    "amountGross": 125,
                    "amountGrossCard": null,
                    "journalAccountCode": "474230",
                    "journalPayee": "CBCP",
                    "journalPayer": "COMP",
                    "cardTransactionReferenceNumber": null,
                    "amountNetOfReclaim": 125,
                    "amountNetOfTax": 125,
                    "taxGuid": [],
                    "accountingTransactionType": null
                  }
                ],
                "tax": []
              }
            ],
            "liabilityAccountCode": null,
            "entryExchangeRateDirection": "M",
            "entryReceiptType": "N",
            "entryVendorDescription": "Marriott Hotels",
            "entryIsPersonal": "N",
            "legacyEntryId": 4252,
            "expenseTypeName": "Room Rate",
            "entryDate": "2019-06-04T00:00:00.000Z",
            "entryCurrAlphaCode": "USD",
            "entryExchangeRate": 1,
            "expenseTypeCode": "LODNG",
            "cardStatementPeriodStartDate": null,
            "cardStatementPeriodEndDate": null,
            "reportEntryPatKey": "1000"
          },
          {
            "expensePayIndicator": "N",
            "clearingAccountCode": "199999",
            "cardProgramTypeCode": null,
            "entryApprovedAmount": 0,
            "entryId": "030A284505775545B95ACF75DBE99652",
            "entryDescription": "In-room movie",
            "entryVendorCode": "Marriott Hotels",
            "entryCustom1Value": null,
            "entryCustom2Value": null,
            "entryCustom3Value": null,
            "entryCustom4Value": null,
            "entryCustom5Value": null,
            "entryCustom6Value": null,
            "entryCustom7Value": null,
            "entryCustom8Value": null,
            "entryCustom9Value": null,
            "entryCustom10Value": null,
            "entryCustom11Value": null,
            "entryCustom12Value": null,
            "entryCustom13Value": null,
            "entryCustom14Value": null,
            "entryCustom15Value": null,
            "entryCustom16Value": null,
            "entryCustom17Value": null,
            "entryCustom18Value": null,
            "entryCustom19Value": null,
            "entryCustom20Value": null,
            "entryCustom21Value": null,
            "entryCustom22Value": null,
            "entryCustom23Value": null,
            "entryCustom24Value": null,
            "entryCustom25Value": null,
            "entryCustom26Value": null,
            "entryCustom27Value": null,
            "entryCustom28Value": null,
            "entryCustom29Value": null,
            "entryCustom30Value": null,
            "entryCustom31Value": null,
            "entryCustom32Value": null,
            "entryCustom33Value": null,
            "entryCustom34Value": null,
            "entryCustom35Value": null,
            "entryCustom36Value": null,
            "entryCustom37Value": null,
            "entryCustom38Value": null,
            "entryCustom39Value": null,
            "entryCustom40Value": null,
            "entryOrgUnit1Value": "EhP6TestSysTravelCareerOD",
            "entryOrgUnit2Value": "TemOD US 2",
            "entryOrgUnit3Value": "Cost Center",
            "entryOrgUnit4Value": "TemOD 0021-Bellevue1",
            "entryOrgUnit5Value": null,
            "entryOrgUnit6Value": null,
            "entryLocationName": "San Francisco",
            "entryReceiptId": null,
            "entryElectronicReceiptId": null,
            "entryCustom4Code": null,
            "entryCustom5Code": null,
            "entryCustom6Code": null,
            "entryCustom7Code": null,
            "entryCustom8Code": null,
            "entryCustom9Code": null,
            "entryCustom10Code": null,
            "entryCustom11Code": null,
            "entryCustom12Code": null,
            "entryCustom13Code": null,
            "entryCustom14Code": null,
            "entryCustom15Code": null,
            "entryCustom16Code": null,
            "entryCustom17Code": null,
            "entryCustom18Code": null,
            "entryCustom19Code": null,
            "entryCustom20Code": null,
            "entryCustom21Code": null,
            "entryCustom22Code": null,
            "entryCustom23Code": null,
            "entryCustom24Code": null,
            "entryCustom25Code": null,
            "entryCustom26Code": null,
            "entryCustom27Code": null,
            "entryCustom28Code": null,
            "entryCustom29Code": null,
            "entryCustom30Code": null,
            "entryCustom31Code": null,
            "entryCustom32Code": null,
            "entryCustom33Code": null,
            "entryCustom34Code": null,
            "entryCustom35Code": "US",
            "entryCustom36Code": null,
            "entryCustom37Code": null,
            "entryCustom38Code": "",
            "entryCustom39Code": "0.00000000",
            "entryCustom40Code": "0E-8",
            "reportEntryTransactionAmount": 14,
            "entryLocationCityName": "San Francisco",
            "entryCountrySubCode": "US-CA",
            "entryIsBillable": "N",
            "entryOrgUnit1Code": "Q16CLNT500",
            "entryOrgUnit2Code": "0021",
            "offsetPayType": "N",
            "entryCountryCode": "US",
            "entryUuid": null,
            "entrySupplierTaxID": null,
            "entryCustom1Code": null,
            "entryCustom2Code": null,
            "entryCustom3Code": null,
            "entryOrgUnit3Code": "CC",
            "entryOrgUnit4Code": "21-BELLEV1",
            "entryOrgUnit5Code": null,
            "entryOrgUnit6Code": null,
            "cardAccountID": null,
            "cardTransactionID": null,
            "cardTransactionAmount": null,
            "cardTransactionCurrency": null,
            "cardTransactionPostedAmount": null,
            "cardTransactionPostedCurrency": null,
            "allocation": [
              {
                "allocationPercentage": null,
                "allocationId": null,
                "allocationCustom1Code": null,
                "allocationCustom2Code": null,
                "allocationCustom3Code": null,
                "allocationCustom4Code": null,
                "allocationCustom5Code": null,
                "allocationCustom6Code": null,
                "allocationCustom7Code": null,
                "allocationCustom8Code": null,
                "allocationCustom9Code": null,
                "allocationCustom10Code": null,
                "allocationCustom11Code": null,
                "allocationCustom12Code": null,
                "allocationCustom13Code": null,
                "allocationCustom14Code": null,
                "allocationCustom15Code": null,
                "allocationCustom16Code": null,
                "allocationCustom17Code": null,
                "allocationCustom18Code": null,
                "allocationCustom19Code": null,
                "allocationCustom20Code": null,
                "allocationCustom1Value": null,
                "allocationCustom2Value": null,
                "allocationCustom3Value": null,
                "allocationCustom4Value": null,
                "allocationCustom5Value": null,
                "allocationCustom6Value": null,
                "allocationCustom7Value": null,
                "allocationCustom8Value": null,
                "allocationCustom9Value": null,
                "allocationCustom10Value": null,
                "allocationCustom11Value": null,
                "allocationCustom12Value": null,
                "allocationCustom13Value": null,
                "allocationCustom14Value": null,
                "allocationCustom15Value": null,
                "allocationCustom16Value": null,
                "allocationCustom17Value": null,
                "allocationCustom18Value": null,
                "allocationCustom19Value": null,
                "allocationCustom20Value": null,
                "journal": [
                  {
                    "amountGross": 14,
                    "amountGrossCard": null,
                    "journalAccountCode": "199999",
                    "journalPayee": "CBCP",
                    "journalPayer": "COMP",
                    "cardTransactionReferenceNumber": null,
                    "amountNetOfReclaim": 14,
                    "amountNetOfTax": 14,
                    "taxGuid": [],
                    "accountingTransactionType": null
                  },
                  {
                    "amountGross": -14,
                    "amountGrossCard": null,
                    "journalAccountCode": "199999",
                    "journalPayee": "COMP",
                    "journalPayer": "EMPL",
                    "cardTransactionReferenceNumber": null,
                    "amountNetOfReclaim": -14,
                    "amountNetOfTax": -14,
                    "taxGuid": [],
                    "accountingTransactionType": null
                  }
                ],
                "tax": []
              }
            ],
            "liabilityAccountCode": null,
            "entryExchangeRateDirection": "M",
            "entryReceiptType": "N",
            "entryVendorDescription": "Marriott Hotels",
            "entryIsPersonal": "Y",
            "legacyEntryId": 4255,
            "expenseTypeName": "Entertainment-Other",
            "entryDate": "2019-06-05T00:00:00.000Z",
            "entryCurrAlphaCode": "USD",
            "entryExchangeRate": 1,
            "expenseTypeCode": "ENTOT",
            "cardStatementPeriodStartDate": null,
            "cardStatementPeriodEndDate": null,
            "reportEntryPatKey": "1000"
          }
        ],
        "cashAdvanceApplication": []
      },
      "docStatus": "READY"
    }
  ],
  "offset": null,
  "nextPage": null,
  "numberReturned": 1
}